osu_beatmap_downloader/__init__.py
osu_beatmap_downloader/downloader.py
osu_beatmap_downloader-0.1.7.dist-info/entry_points.txt
osu_beatmap_downloader-0.1.7.dist-info/LICENSE
osu_beatmap_downloader-0.1.7.dist-info/WHEEL
osu_beatmap_downloader-0.1.7.dist-info/METADATA
osu_beatmap_downloader-0.1.7.dist-info/RECORD
