Metadata-Version: 2.1
Name: osu-beatmap-downloader
Version: 0.1.7
Summary: Downloads x most favorized beatmapsets into the current directory
Home-page: https://github.com/vincentmathis/osu-beatmap-downloader
License: GPL-3.0
Keywords: osu!,osu,beatmaps,downloader
Author: Vincent Mathis
Author-email: vincentmathis@protonmail.com
Requires-Python: >=3.10,<4.0
Classifier: License :: OSI Approved :: GNU General Public License v3 (GPLv3)
Classifier: Programming Language :: Python :: 3
Classifier: Programming Language :: Python :: 3.10
Requires-Dist: inquirerpy (>=0.3.3,<0.4.0)
Requires-Dist: loguru (>=0.4.1,<0.5.0)
Requires-Dist: requests (>=2.23.0,<3.0.0)
Project-URL: Repository, https://github.com/vincentmathis/osu-beatmap-downloader
Project-URL: issues, https://github.com/vincentmathis/osu-beatmap-downloader/issues
